sourmash_utils.py
sourmash_utils-0.3.dist-info/METADATA
sourmash_utils-0.3.dist-info/WHEEL
sourmash_utils-0.3.dist-info/top_level.txt
sourmash_utils-0.3.dist-info/RECORD
