Metadata-Version: 2.4
Name: sourmash_utils
Version: 0.3
Summary: Python utilities for sourmash plugins and scripts
Requires-Python: >=3.10
Requires-Dist: sourmash<5,>=4.9.0
